PyTubeStudio/__init__.py
PyTubeStudio/client.py
VtsModels/__init__.py
VtsModels/models.py
PyTubeStudio-0.1.0.dist-info/LICENSE
PyTubeStudio-0.1.0.dist-info/METADATA
PyTubeStudio-0.1.0.dist-info/WHEEL
PyTubeStudio-0.1.0.dist-info/top_level.txt
PyTubeStudio-0.1.0.dist-info/RECORD
