Metadata-Version: 2.1
Name: PyTubeStudio
Version: 0.1.0
Summary: A library to interact with the VTubeStudio API
Author: Jaarfi
Project-URL: Homepage, https://github.com/jaarfi/PyTubeStudio
Project-URL: Repository, https://github.com/jaarfi/PyTubeStudio
Project-URL: Issues, https://github.com/jaarfi/PyTubeStudio/issues
Project-URL: Stream, https://www.twitch.tv/jaarfi
Classifier: Programming Language :: Python :: 3
Classifier: License :: OSI Approved :: MIT License
Classifier: Operating System :: OS Independent
Requires-Python: >=3.8
License-File: LICENSE
Requires-Dist: pydantic >=2.7
Requires-Dist: websockets >=12.0
Requires-Dist: platformdirs
Requires-Dist: aiofiles
